flask_cloudflare_login/__init__.py
flask_cloudflare_login/access.py
flask_cloudflare_login-0.7.5.dist-info/METADATA
flask_cloudflare_login-0.7.5.dist-info/WHEEL
flask_cloudflare_login-0.7.5.dist-info/licenses/LICENSE
flask_cloudflare_login-0.7.5.dist-info/RECORD
