Metadata-Version: 2.1
Name: flask_cloudflare_login
Version: 0.7.5
Summary: The Flask Cloudflare Login module provides a Flask-Login user class from Cloudfare Access JWT token and Cloudflare identity API
Project-URL: Homepage, https://github.com/norrbom/flask_cloudflare_login
Author-email: Anders Norrbom <anders@norrbom.org>
License-Expression: MIT
License-File: LICENSE
Classifier: Operating System :: OS Independent
Classifier: Programming Language :: Python :: 3
Requires-Python: >=3.8
Requires-Dist: cachetools>=5.3.0
Requires-Dist: pyjwt>=2.6.0
Requires-Dist: requests>=2.28.2
